demo/client.py
mcp-tutorial/__init__.py
mcp-tutorial/examples/__init__.py
mcp-tutorial/examples/client.py
mcp-tutorial/examples/modelservice_mcp_example.py
mcp-tutorial/examples/test_composing.py
mcp-tutorial/examples/servers/advanced.py
mcp-tutorial/examples/servers/fastapi_example.py
mcp-tutorial/examples/servers/sse.py
mcp-tutorial/examples/servers/stdio.py
mcp-tutorial/examples/servers/streamable_http.py
mcp-tutorial/examples/servers/project/advanced.py
mcpy_cli/__init__.py
mcpy_cli/__main__.py
mcpy_cli/discovery.py
mcpy_cli/mcp_event_store.py
mcpy_cli/packaging.py
mcpy_cli/packaging_utils.py
mcpy_cli/app_builder/__init__.py
mcpy_cli/app_builder/application_factory.py
mcpy_cli/app_builder/caching.py
mcpy_cli/app_builder/instance_factory.py
mcpy_cli/app_builder/middleware.py
mcpy_cli/app_builder/mocking.py
mcpy_cli/app_builder/routing.py
mcpy_cli/app_builder/validation.py
mcpy_cli/cli/__init__.py
mcpy_cli/cli/config.py
mcpy_cli/cli/imports.py
mcpy_cli/cli/main.py
mcpy_cli/cli/commands/__init__.py
mcpy_cli/cli/commands/example.py
mcpy_cli/cli/commands/package.py
mcpy_cli/cli/commands/run.py
mcpy_cli/examples/run_with_event_store.py
mcpy_cli/examples/run_with_mcp_event_store.py
mcpy_cli/examples/test_cli_with_event_store.py
mcpy_cli/examples/test_mcp_event_store.py
mcpy_cli/templates/README.md.template
mcpy_cli/templates/README_zh.md.template
mcpy_cli/templates/start.sh.template
mcpy_cli/utils/__init__.py
mcpy_cli/utils/exceptions.py
mcpy_cli/utils/logging_utils.py
mcpy_cli/utils/path_utils.py
mcpy_cli/utils/schema_utils.py
mcpy_cli-0.3.8.dist-info/METADATA
mcpy_cli-0.3.8.dist-info/WHEEL
mcpy_cli-0.3.8.dist-info/entry_points.txt
mcpy_cli-0.3.8.dist-info/top_level.txt
mcpy_cli-0.3.8.dist-info/RECORD
