Metadata-Version: 2.4
Name: mcpy-cli
Version: 0.3.8
Summary: A CLI for the MCP Modelservice Example
Author: Haotian Liu @heywhale
License: MIT
Project-URL: Homepage, https://github.com/liuhaotian9420/mcp
Project-URL: Repository, https://github.com/liuhaotian9420/mcp
Project-URL: Documentation, https://github.com/liuhaotian9420/mcp/docs
Project-URL: Bug Tracker, https://github.com/liuhaotian9420/mcp/issues
Keywords: mcp,model-context-protocol,fastapi,cli,fastmcp
Classifier: Development Status :: 4 - Beta
Classifier: Intended Audience :: Developers
Classifier: License :: OSI Approved :: MIT License
Classifier: Programming Language :: Python :: 3
Classifier: Programming Language :: Python :: 3.10
Classifier: Programming Language :: Python :: 3.11
Classifier: Programming Language :: Python :: 3.12
Classifier: Topic :: Software Development :: Libraries :: Python Modules
Classifier: Topic :: Internet :: WWW/HTTP :: HTTP Servers
Classifier: Topic :: System :: Networking
Requires-Python: >=3.10
Requires-Dist: mcp[cli]>=1.3.0
Requires-Dist: fastapi>=0.110.0
Requires-Dist: fastapi-mcp<=0.3.4
Requires-Dist: pydantic>=2.0.0
Requires-Dist: requests>=2.25.0
Requires-Dist: typer>=0.9.0
Requires-Dist: uvicorn>=0.20.0
Requires-Dist: python-dotenv>=0.15.0
Requires-Dist: fastmcp>=2.2.0
Provides-Extra: test
Requires-Dist: ruff>=0.9.10; extra == "test"
Requires-Dist: mypy>=1.0.0; extra == "test"
Requires-Dist: build>=1.0.0; extra == "test"
Requires-Dist: twine>=4.0.0; extra == "test"
